phonologic/__init__.py
phonologic/_eval.py
phonologic/_exceptions.py
phonologic/_load.py
phonologic/_logging.py
phonologic/_systems.py
phonologic/analysis.py
phonologic/_error_analysis/__init__.py
phonologic/_error_analysis/_analyze.py
phonologic/_error_analysis/_levenshtein.py
phonologic/_file_parsing/__init__.py
phonologic/_file_parsing/_parser.py
phonologic/_file_parsing/_spec.py
phonologic/_file_parsing/_tokenizer.py
phonologic/_file_parsing/ipa-to-arpabet.json
phonologic/systems/__init__.py
phonologic/systems/hayes-arpabet.phl
phonologic/systems/hayes.phl
phonologic/viewer/__init__.py
phonologic/viewer/viewer.py
phonologic/viewer/web/404.html
phonologic/viewer/web/index.html
phonologic/viewer/web/style.css
phonologic/viewer/web/components/AlignedSteps.js
phonologic/viewer/web/components/App.js
phonologic/viewer/web/components/AudioPlayer.js
phonologic/viewer/web/components/Details.js
phonologic/viewer/web/components/Features.js
phonologic/viewer/web/components/TranscriptFormatted.js
tests/__init__.py
tests/example.json
tests/test_feature_distance.py
tests/test_feature_lookup.py
tests/test_levenshtein.py
tests/test_parse.py
tests/test_phoneme_distance.py
tests/test_phoneme_tokenizer.py
tests/test_system.py
tests/test_system_hayes.py
tests/test_data/__init__.py
tests/test_data/arpabet-to-ipa.json
tests/test_data/ipa-to-arpabet.json
phonologic-0.2.0.dist-info/METADATA
phonologic-0.2.0.dist-info/WHEEL
phonologic-0.2.0.dist-info/entry_points.txt
phonologic-0.2.0.dist-info/top_level.txt
phonologic-0.2.0.dist-info/RECORD
