Metadata-Version: 2.1
Name: phonologic
Version: 0.2.0
Home-page: https://github.com/rcgale/phonologic
Author: Robert Gale
Author-email: galer@ohsu.edu
Requires-Dist: regex
Requires-Dist: tqdm
